example/app.py
src/conger/__init__.py
src/conger/core.py
src/conger/database.py
src/conger/model.py
src/conger/schema.py
congers-0.1.0.dist-info/METADATA
congers-0.1.0.dist-info/WHEEL
congers-0.1.0.dist-info/licenses/LICENSE
congers-0.1.0.dist-info/RECORD
