Metadata-Version: 2.1
Name: congers
Version: 0.1.0
Summary: A Lightweight data model management for Python
Author-email: chaojie <hi@chaojie.fun>
License-File: LICENSE
Requires-Python: >=3.8
Requires-Dist: flask-cors~=3.0.10
Requires-Dist: flask~=2.3.2
Requires-Dist: pydantic~=1.10.8
